text_gen/__init__.py
text_gen/pytorch_textgen.py
text_gen/ten_textgen.py
text_gen/tensor_textgen.py
text_gen-1.9.0.dist-info/METADATA
text_gen-1.9.0.dist-info/WHEEL
text_gen-1.9.0.dist-info/top_level.txt
text_gen-1.9.0.dist-info/RECORD
